kslurm/__init__.py
kslurm/appcache.py
kslurm/appconfig.py
kslurm/args/__init__.py
kslurm/args/actions.py
kslurm/args/arg.py
kslurm/args/arg_types.py
kslurm/args/arg_types.pyi
kslurm/args/command.py
kslurm/args/help.py
kslurm/args/help_templates.py
kslurm/args/helpers.py
kslurm/args/matchers.py
kslurm/args/parser.py
kslurm/args/protocols.py
kslurm/bin/__init__.py
kslurm/bin/bash.sh
kslurm/bin/kpy-init.sh
kslurm/bin/kpy-wrapper.sh
kslurm/bin/neuroglia-helpers.sh
kslurm/cli/__init__.py
kslurm/cli/config.py
kslurm/cli/kapp/__init__.py
kslurm/cli/kapp/alias.py
kslurm/cli/kapp/image.py
kslurm/cli/kapp/main.py
kslurm/cli/kbatch.py
kslurm/cli/kjupyter.py
kslurm/cli/kpy.py
kslurm/cli/krun.py
kslurm/cli/main.py
kslurm/cli/ssnake.py
kslurm/container.py
kslurm/data/__init__.py
kslurm/data/download_frozen_container.hash
kslurm/data/slurm_job_templates.json
kslurm/exceptions.py
kslurm/installer/__init__.py
kslurm/installer/installer.py
kslurm/installer/utils.py
kslurm/installer/version.py
kslurm/models/__init__.py
kslurm/models/formatters.py
kslurm/models/job_templates.py
kslurm/models/slurm.py
kslurm/models/update.py
kslurm/models/validators.py
kslurm/shell.py
kslurm/slurm/__init__.py
kslurm/slurm/helpers.py
kslurm/slurm/slurm_command.py
kslurm/style/__init__.py
kslurm/style/console.py
kslurm/style/themes.py
kslurm/test/__init__.py
kslurm/test/args/__init__.py
kslurm/test/args/test_model_parsing.py
kslurm/test/args/test_parser.py
kslurm/test/installer/fake_releases.json
kslurm/test/installer/test_install.py
kslurm/test/installer/test_utils.py
kslurm/test/test_batch.py
kslurm/test/test_help.py
kslurm/test/test_slurm_helpers.py
kslurm/test/test_validators.py
kslurm/text.py
kslurm/utils.py
kslurm/venv.py
neuroglia_helpers/.git
neuroglia_helpers/.github/workflows/valdate_bids-apps.tsv.yml
neuroglia_helpers/.github_scripts/install_singularity.sh
neuroglia_helpers/00_init.sh
neuroglia_helpers/00_initrc.sh
neuroglia_helpers/LICENSE
neuroglia_helpers/README.md
kslurm-0.6.4.dist-info/LICENSE
kslurm-0.6.4.dist-info/METADATA
kslurm-0.6.4.dist-info/WHEEL
kslurm-0.6.4.dist-info/entry_points.txt
kslurm-0.6.4.dist-info/RECORD
