Metadata-Version: 2.1
Name: kslurm
Version: 0.6.4
Summary: Helper scripts and wrappers for running commands on SLURM compute clusters.
Home-page: https://github.com/pvandyken/kslurm
License: MIT
Keywords: slurm,compute cluster
Author: Peter Van Dyken
Author-email: pvandyk2@uwo.ca
Requires-Python: >=3.9,<4.0
Classifier: Development Status :: 4 - Beta
Classifier: Environment :: Console
Classifier: Intended Audience :: Science/Research
Classifier: License :: OSI Approved :: MIT License
Classifier: Natural Language :: English
Classifier: Operating System :: POSIX :: Linux
Classifier: Programming Language :: Python :: 3
Classifier: Programming Language :: Python :: 3.9
Classifier: Programming Language :: Python :: 3.10
Classifier: Programming Language :: Python :: 3.11
Classifier: Programming Language :: Python :: 3.12
Classifier: Programming Language :: Python :: 3.7
Classifier: Programming Language :: Python :: 3.8
Classifier: Topic :: Utilities
Classifier: Typing :: Typed
Requires-Dist: InquirerPy (>=0.3.3,<0.4.0)
Requires-Dist: Pint (>=0.19.2,<0.20.0)
Requires-Dist: appdirs (>=1.4.4,<2.0.0)
Requires-Dist: attrs (>=21.2.0,<22.0.0)
Requires-Dist: colorama (>=0.4.4,<0.5.0)
Requires-Dist: docstring-parser (>=0.14.1,<0.15.0)
Requires-Dist: flake8 (>=4.0.1,<5.0.0)
Requires-Dist: more-itertools (>=8.13.0,<9.0.0)
Requires-Dist: requests (>=2.27.1,<3.0.0)
Requires-Dist: rich (>=12.2.0,<13.0.0)
Requires-Dist: semver (>=2.13.0,<3.0.0)
Requires-Dist: shellingham (>=1.4.0,<2.0.0)
Requires-Dist: tabulate (>=0.8.9,<0.9.0)
Requires-Dist: typing-extensions (>=3.10)
Requires-Dist: virtualenv (>=20.0.24,<21)
Requires-Dist: yaspin (>=2.2.0,<3.0.0)
Project-URL: Repository, https://github.com/pvandyken/kslurm
